vscodedebugvisualizer/Visualize.py
vscodedebugvisualizer/__init__.py
vscodedebugvisualizer/__main__.py
vscodedebugvisualizer/visualizer/DirectVisualizer.py
vscodedebugvisualizer/visualizer/GeoPandasVisualizer.py
vscodedebugvisualizer/visualizer/ListVisualizer.py
vscodedebugvisualizer/visualizer/MultiLineNumpyVisualizer.py
vscodedebugvisualizer/visualizer/NumpyVisualizer.py
vscodedebugvisualizer/visualizer/PandasVisualizer.py
vscodedebugvisualizer/visualizer/PlotlyVisualizer.py
vscodedebugvisualizer/visualizer/PrimitiveVisualizer.py
vscodedebugvisualizer/visualizer/PyTorchVisualizer.py
vscodedebugvisualizer/visualizer/ShapelyVisualizer.py
vscodedebugvisualizer/visualizer/TensorflowVisualizer.py
vscodedebugvisualizer/visualizer/__init__.py
vscodedebugvisualizer-0.2.1.dist-info/licenses/LICENSE
vscodedebugvisualizer-0.2.1.dist-info/METADATA
vscodedebugvisualizer-0.2.1.dist-info/WHEEL
vscodedebugvisualizer-0.2.1.dist-info/top_level.txt
vscodedebugvisualizer-0.2.1.dist-info/RECORD
